miller_rabin.cpython-36m-x86_64-linux-gnu.so
miller_rabin/py.typed
miller_rabin/__init__.pyi
miller_rabin-1.0.1.dist-info/WHEEL
miller_rabin-1.0.1.dist-info/COPYING.gmp
miller_rabin-1.0.1.dist-info/METADATA
miller_rabin-1.0.1.dist-info/COPYING
miller_rabin-1.0.1.dist-info/RECORD
miller_rabin-1.0.1.dist-info/COPYING.techneon
miller_rabin-1.0.1.dist-info/top_level.txt
miller_rabin-1.0.1.dist-info/COPYING.boost
miller_rabin.libs/libgmp-00702cd1.so.10.3.2
