Metadata-Version: 2.1
Name: miller-rabin
Version: 1.0.1
Summary: Fast, deterministic* Miller-Rabin primality test.
Home-page: https://github.com/zmwangx/miller-rabin
Author: Zhiming Wang
Author-email: pypi@zhimingwang.org
License: MIT
Platform: UNKNOWN
Classifier: Development Status :: 5 - Production/Stable
Classifier: Intended Audience :: Developers
Classifier: Intended Audience :: Education
Classifier: Intended Audience :: Science/Research
Classifier: License :: OSI Approved :: MIT License
Classifier: Operating System :: OS Independent
Classifier: Programming Language :: Python :: 3
Classifier: Programming Language :: Python :: 3.6
Classifier: Programming Language :: Python :: 3.7
Classifier: Programming Language :: Python :: 3.8
Classifier: Programming Language :: Python :: 3 :: Only
Classifier: Programming Language :: Python :: Implementation :: CPython
Classifier: Topic :: Scientific/Engineering
Classifier: Topic :: Scientific/Engineering :: Mathematics
Classifier: Typing :: Typed
Requires-Python: >=3.6
Provides-Extra: bench
Requires-Dist: gmpy2 ; extra == 'bench'
Requires-Dist: py-cpuinfo ; extra == 'bench'
Provides-Extra: dev
Requires-Dist: pytest ; extra == 'dev'
Requires-Dist: gmpy2 ; extra == 'dev'
Requires-Dist: py-cpuinfo ; extra == 'dev'
Provides-Extra: tests
Requires-Dist: pytest ; extra == 'tests'
